banner_jeong/__init__.py
banner_jeong/banner.py
banner_jeong/pic.py
banner_jeong-0.4.2.dist-info/METADATA
banner_jeong-0.4.2.dist-info/WHEEL
banner_jeong-0.4.2.dist-info/entry_points.txt
banner_jeong-0.4.2.dist-info/top_level.txt
banner_jeong-0.4.2.dist-info/RECORD
