Metadata-Version: 2.1
Name: banner_jeong
Version: 0.4.2
Summary: show design text
Author-email: Jeonghoon2 <ukidd12@naver.com>
License: MIT
Project-URL: Homepage, https://github.com/Jeonghoon2/banner_jeong
Project-URL: Issues, https://github.com/Jeonghoon2/banner_jeong/issues
Requires-Python: >=3.9
Requires-Dist: pyfiglet >=1.0.2
